EngeSpec/EngeSpec.py
EngeSpec/__init__.py
EngeSpec/testboost.py
EngeSpec-0.0.1.dist-info/LICENSE
EngeSpec-0.0.1.dist-info/METADATA
EngeSpec-0.0.1.dist-info/WHEEL
EngeSpec-0.0.1.dist-info/top_level.txt
EngeSpec-0.0.1.dist-info/RECORD
