Metadata-Version: 2.1
Name: EngeSpec
Version: 0.0.1
Summary: A GUI for data acquisition systems
Home-page: https://github.com/pypa/sampleproject
Author: Richar Longland
Author-email: richard_longland@ncsu.edu
License: UNKNOWN
Platform: UNKNOWN
Classifier: Programming Language :: Python :: 3
Classifier: License :: OSI Approved :: MIT License
Classifier: Operating System :: OS Independent
Requires-Python: >=3.6
